{"is_source_file": false, "format": "", "description": "", "external_files": [], "external_methods": [], "published": [], "classes": [], "methods": [], "calls": [], "search-terms": [], "state": 2, "file_id": 17, "knowledge_revision": 39, "git_revision": "ab4b8dda370bc087103ebfe015d1017f08367b81", "hash": "20cc8dde8a4e6bd1a98f85635ff84539", "format-version": 4, "code-base-name": "notes_frontend", "filename": "notes_frontend/README_NOTES_APP.md", "revision_history": [{"39": "ab4b8dda370bc087103ebfe015d1017f08367b81"}]}